SmallDevops/__init__.py
SmallDevops/__main__.py
SmallDevops/__version__.py
SmallDevops/core/__init__.py
SmallDevops/core/__version__.py
SmallDevops/core/devop.py
SmallDevops/core/execute_cli.py
SmallDevops/template_class/__init__.py
SmallDevops/template_class/base_class_test.py
SmallDevops/template_class/pytest_timing_git.py
SmallDevops/template_class/unittest_timing_git.py
SmallDevops/template_class/unittest_timing_git_python27.py
SmallDevops/website_file/file.html
SmallDevops-1.2.1.dist-info/LICENSE
SmallDevops-1.2.1.dist-info/METADATA
SmallDevops-1.2.1.dist-info/WHEEL
SmallDevops-1.2.1.dist-info/top_level.txt
SmallDevops-1.2.1.dist-info/RECORD
