Metadata-Version: 2.1
Name: SmallDevops
Version: 1.2.1
Summary: free script for continuous integration (CI).
Home-page: https://github.com/0pb/smalldevops
Author: 0pb
License: GNU V3
Platform: UNKNOWN
Classifier: Intended Audience :: Developers
Classifier: License :: OSI Approved :: GNU Lesser General Public License v3 or later (LGPLv3+)
Classifier: Operating System :: POSIX :: Linux
Classifier: Programming Language :: Python
Classifier: Programming Language :: Python :: 3
Classifier: Topic :: Software Development :: Testing
Requires-Python: >=3.6.0
